powermv/__main__.py
powermv/matching.py
powermv/operations.py
powermv/rendering.py
powermv/utils.py
powermv-0.3.1.dist-info/METADATA
powermv-0.3.1.dist-info/WHEEL
powermv-0.3.1.dist-info/entry_points.txt
powermv-0.3.1.dist-info/top_level.txt
powermv-0.3.1.dist-info/RECORD
