Metadata-Version: 2.4
Name: powermv
Version: 0.3.1
Summary: Add your description here
Requires-Python: >=3.12
Requires-Dist: cyclopts>=3.4.1
Requires-Dist: jinja2>=3.1.5
Requires-Dist: networkx>=3.4.2
Requires-Dist: pyparsing>=3.2.1
